MANIFEST.in
README.md
setup.py
djams/__init__.py
djams/admin.py
djams/apps.py
djams/audit_trail.py
djams/config_vars.py
djams/decorators.py
djams/djams_forms.py
djams/djams_model_views.py
djams/djams_settings.py
djams/middleware.py
djams/models.py
djams/tests.py
djams/urls.py
djams/utils.py
djams/views.py
djams.egg-info/PKG-INFO
djams.egg-info/SOURCES.txt
djams.egg-info/dependency_links.txt
djams.egg-info/requires.txt
djams.egg-info/top_level.txt
djams/migrations/0001_initial.py
djams/migrations/__init__.py
djams/migrations/old/0001_initial.py
djams/migrations/old/0002_mds_partytype_partyclass.py
djams/migrations/old/0003_auto_20181023_2302.py
djams/migrations/old/0004_adm_app_description.py
djams/migrations/old/0005_auto_20181104_0113.py
djams/migrations/old/0006_auto_20181104_0115.py
djams/migrations/old/0007_auto_20181104_1601.py
djams/migrations/old/0008_adm_team_team_members.py
djams/migrations/old/0009_auto_20181105_2315.py
djams/migrations/old/0010_auto_20181105_2330.py
djams/migrations/old/0011_auto_20181108_0024.py
djams/static/djams/css/all.min.css
djams/static/djams/css/bootstrap.min.css
djams/static/djams/css/bootstrap.min.css.map
djams/static/djams/css/bootstrap_docs.min.css
djams/static/djams/css/standardized.css
djams/static/djams/images/balloons.jpg
djams/static/djams/images/e-logo.svg
djams/static/djams/images/letter-e.svg
djams/static/djams/images/london.jpg
djams/static/djams/images/molecule.svg
djams/static/djams/images/outlier.jpg
djams/static/djams/images/work_anywhere.jpg
djams/static/djams/webfonts/fa-brands-400.eot
djams/static/djams/webfonts/fa-brands-400.svg
djams/static/djams/webfonts/fa-brands-400.ttf
djams/static/djams/webfonts/fa-brands-400.woff
djams/static/djams/webfonts/fa-brands-400.woff2
djams/static/djams/webfonts/fa-regular-400.eot
djams/static/djams/webfonts/fa-regular-400.svg
djams/static/djams/webfonts/fa-regular-400.ttf
djams/static/djams/webfonts/fa-regular-400.woff
djams/static/djams/webfonts/fa-regular-400.woff2
djams/static/djams/webfonts/fa-solid-900.eot
djams/static/djams/webfonts/fa-solid-900.svg
djams/static/djams/webfonts/fa-solid-900.ttf
