Metadata-Version: 2.1
Name: djams
Version: 0.5.9
Summary: UNKNOWN
Home-page: UNKNOWN
Author: Eddy B
Author-email: 
License: MIT
Keywords: django analytics microsite bindings
Platform: UNKNOWN
Classifier: Development Status :: 3 - Alpha
Classifier: Intended Audience :: Developers
Classifier: License :: OSI Approved :: MIT License
Classifier: Programming Language :: Python :: 3
Requires-Python: >=3.5
